Metadata-Version: 2.1
Name: churn-framework
Version: 0.1.5
Summary: UNKNOWN
Home-page: https://github.com/A3Data/churn-framework
Author: A3Data
Author-email: gustavo.resende@a3data.com.br
License: MIT
Download-URL: https://github.com/A3Data/churn-framework/archive/refs/tags/0.1.tar.gz
Keywords: framework,churn,metric,optimizer
Platform: UNKNOWN
Classifier: Development Status :: 3 - Alpha
Classifier: Topic :: Software Development :: Build Tools
Classifier: License :: OSI Approved :: MIT License
Classifier: Programming Language :: Python :: 3.6
Classifier: Programming Language :: Python :: 3.7
Classifier: Programming Language :: Python :: 3.8
License-File: LICENSE.txt
